[
	{ "firstname": "Andrew", "lastname": "Howes", "gitHandle": "andrewhws", "location": "Los Angeles, CA.", "imgsrc": "./0.jpg" },
	{ "firstname": "Aram", "lastname": "Simonian", "gitHandle": "aram91", "location": "Los Angeles, CA.", "imgsrc": "./1.jpg" },
	{ "firstname": "Casandra", "lastname": "Silva", "gitHandle": "casandrawith1s", "location": "Los Angeles, CA.", "imgsrc": "./2.jpg" },
	{ "firstname": "Chelsea", "lastname": "Cheung", "gitHandle": "chelseatcheung", "location": "Los Angeles, CA.", "imgsrc": "./3.jpg" },
	{ "firstname": "Cory", "lastname": "Dang", "gitHandle": "coryd4ng", "location": "Los Angeles, CA.", "imgsrc": "./4.jpg" },
	{ "firstname": "Seyi", "lastname": "Williams", "gitHandle": "git2go", "location": "Los Angeles, CA.", "imgsrc": "./5.jpg" },
	{ "firstname": "Jeffrey", "lastname": "Yang", "gitHandle": "jeffycyang", "location": "Los Angeles, CA.", "imgsrc": "./6.jpg" },
	{ "firstname": "Jonathan", "lastname": "Kvicky", "gitHandle": "jonkvix", "location": "Los Angeles, CA.", "imgsrc": "./7.jpg" },
	{ "firstname": "Jonathan", "lastname": "Tamsut", "gitHandle": "jtamsut", "location": "Los Angeles, CA.", "imgsrc": "./8.jpg" },
	{ "firstname": "Kevin", "lastname": "Cheng", "gitHandle": "k-cheng", "location": "Los Angeles, CA.", "imgsrc": "./9.jpg" },
	{ "firstname": "Marc", "lastname": "Reicher", "gitHandle": "marcreicher", "location": "Los Angeles, CA.", "imgsrc": "./10.jpg" },
	{ "firstname": "Marcus", "lastname": "Ellis", "gitHandle": "marcusmellis89", "location": "Los Angeles, CA.", "imgsrc": "./11.jpg" },
	{ "firstname": "Mike", "lastname": "Martin", "gitHandle": "martinms-usc", "location": "Los Angeles, CA.", "imgsrc": "./12.jpg" },
	{ "firstname": "Matt", "lastname": "Murkidjanian", "gitHandle": "mmurkidjanian", "location": "Los Angeles, CA.", "imgsrc": "./13.jpg" },
	{ "firstname": "Nick", "lastname": "Krein", "gitHandle": "nkreinmusic", "location": "Los Angeles, CA.", "imgsrc": "./14.jpg" },
	{ "firstname": "Stephanie", "lastname": "Raad", "gitHandle": "Stephyraad", "location": "Los Angeles, CA.", "imgsrc": "./15.jpg" },
	{ "firstname": "Avi", "lastname": "Samloff", "gitHandle": "theavish", "location": "Los Angeles, CA.", "imgsrc": "./16.jpg" },
	{ "firstname": "Timothy", "lastname": "Lai", "gitHandle": "tim-lai", "location": "Los Angeles, CA.", "imgsrc": "./17.jpg" },
	{ "firstname": "Tina", "lastname": "Lai", "gitHandle": "tinalai", "location": "Los Angeles, CA.", "imgsrc": "./18.jpg" },
	{ "firstname": "Vidiu", "lastname": "Chew", "gitHandle": "VDUCHEW", "location": "Los Angeles, CA.", "imgsrc": "./19.jpg" },
	{ "firstname": "William", "lastname": "Carroll", "gitHandle": "wpcarro", "location": "Los Angeles, CA.", "imgsrc": "./20.jpg" },
	{ "firstname": "Zachary", "lastname": "Cherries", "gitHandle": "zcherries", "location": "Los Angeles, CA.", "imgsrc": "./21.jpg" }
]